pg_async_events/__init__.py
pg_async_events/events.py
pg_async_events-0.1.2.dist-info/LICENSE
pg_async_events-0.1.2.dist-info/METADATA
pg_async_events-0.1.2.dist-info/WHEEL
pg_async_events-0.1.2.dist-info/top_level.txt
pg_async_events-0.1.2.dist-info/RECORD
