Metadata-Version: 2.1
Name: pg-async-events
Version: 0.1.2
Summary: A simple async event handling library using PostgreSQL notifications.
Home-page: https://github.com/255BITS/pg-async-events
Author: Martyn Garcia
Author-email: martyn@255bits.com
License: MIT
Classifier: Development Status :: 4 - Beta
Classifier: Programming Language :: Python :: 3
Classifier: Programming Language :: Python :: 3.8
Classifier: Programming Language :: Python :: 3.9
Classifier: Programming Language :: Python :: 3.10
Classifier: Programming Language :: Python :: 3.11
Classifier: Programming Language :: Python :: 3.12
Classifier: License :: OSI Approved :: MIT License
Classifier: Operating System :: OS Independent
Requires-Python: >=3.8
License-File: LICENSE
Requires-Dist: asyncpg >=0.24.0
